Metadata-Version: 1.0
Name: tools-s
Version: 0.1
Summary: Best of luck
Home-page: UNKNOWN
Author: Fatal anonymous
Author-email: fataanonymous@anonymous.com
License: MIT
Platform: UNKNOWN
